santai_mcp_client/__init__.py
santai_mcp_client/__main__.py
santai_mcp_client/client.py
santai_mcp_client/llm_endpoint.py
santai_mcp_client/models.py
santai_mcp_client/selector.py
santai_mcp_client/tester.py
santai_mcp_client/transport.py
santai_mcp_sdk-0.1.2.dist-info/METADATA
santai_mcp_sdk-0.1.2.dist-info/WHEEL
santai_mcp_sdk-0.1.2.dist-info/top_level.txt
santai_mcp_sdk-0.1.2.dist-info/RECORD
