Metadata-Version: 2.4
Name: santai-mcp-sdk
Version: 0.1.2
Summary: Sant.ai MCP SDK
Author-email: "Sant.ai" <solutions@sant.ai>
Project-URL: Homepage, https://gitlab.com/homere/santai-mcp-sdk
Project-URL: Source, https://gitlab.com/homere/santai-mcp-sdk
Keywords: mcp,client,sdk,llm
Classifier: Programming Language :: Python :: 3
Requires-Python: >=3.11
Requires-Dist: fastmcp>=2.11.1
Provides-Extra: dev
Requires-Dist: ruff>=0.14.0; extra == "dev"
Requires-Dist: pre-commit>=4.3.0; extra == "dev"
Requires-Dist: pytest>=8.0.0; extra == "dev"
Requires-Dist: pytest-asyncio>=0.23.0; extra == "dev"
